{
    "no": 69,
    "name": "سُورَةُ الحَاقَّةِ",
    "enName": "Al-Haaqqa",
    "enNameTranslation": "The Reality",
    "bnNameTranslation": "আল হাককাহ",
    "revelationType": "Meccan",
    "numberOfAyahs": 52,
    "verses": [
        {
            "text": "الْحَاقَّةُ",
            "bnText": "সুনিশ্চিত বিষয়।",
            "enText": "The Inevitable Reality -",
            "enTextTransliteration": "Al haaaqqah",
            "audioPrimary": "https://cdn.alquran.cloud/media/audio/ayah/ar.alafasy/5324",
            "numberInSurah": 1
        },
        {
            "text": "مَا الْحَاقَّةُ",
            "bnText": "সুনিশ্চিত বিষয় কি",
            "enText": "What is the Inevitable Reality?",
            "enTextTransliteration": "Mal haaaqqah",
            "audioPrimary": "https://cdn.alquran.cloud/media/audio/ayah/ar.alafasy/5325",
            "numberInSurah": 2
        },
        {
            "text": "وَمَا أَدْرَاكَ مَا الْحَاقَّةُ",
            "bnText": "আপনি কি কিছু জানেন, সেই সুনিশ্চিত বিষয় কি",
            "enText": "And what can make you know what is the Inevitable Reality?",
            "enTextTransliteration": "Wa maaa adraaka mal haaaqqah",
            "audioPrimary": "https://cdn.alquran.cloud/media/audio/ayah/ar.alafasy/5326",
            "numberInSurah": 3
        },
        {
            "text": "كَذَّبَتْ ثَمُودُ وَعَادٌ بِالْقَارِعَةِ",
            "bnText": "আদ ও সামুদ গোত্র মহাপ্রলয়কে মিথ্যা বলেছিল।",
            "enText": "Thamud and 'Aad denied the Striking Calamity.",
            "enTextTransliteration": "Kazzabat samoodu wa 'Aadum bil qaari'ah",
            "audioPrimary": "https://cdn.alquran.cloud/media/audio/ayah/ar.alafasy/5327",
            "numberInSurah": 4
        },
        {
            "text": "فَأَمَّا ثَمُودُ فَأُهْلِكُوا بِالطَّاغِيَةِ",
            "bnText": "অতঃপর সমুদ গোত্রকে ধ্বংস করা হয়েছিল এক প্রলয়ংকর বিপর্যয় দ্বারা।",
            "enText": "So as for Thamud, they were destroyed by the overpowering [blast].",
            "enTextTransliteration": "Fa-ammaa Samoodu fauhlikoo bittaaghiyah",
            "audioPrimary": "https://cdn.alquran.cloud/media/audio/ayah/ar.alafasy/5328",
            "numberInSurah": 5
        },
        {
            "text": "وَأَمَّا عَادٌ فَأُهْلِكُوا بِرِيحٍ صَرْصَرٍ عَاتِيَةٍ",
            "bnText": "এবং আদ গোত্রকে ধ্বংস করা হয়েছিল এক প্রচন্ড ঝঞ্জাবায়ূ",
            "enText": "And as for 'Aad, they were destroyed by a screaming, violent wind",
            "enTextTransliteration": "Wa ammaa 'Aadun fa uhlikoo bireehin sarsarin 'aatiyah",
            "audioPrimary": "https://cdn.alquran.cloud/media/audio/ayah/ar.alafasy/5329",
            "numberInSurah": 6
        },
        {
            "text": "سَخَّرَهَا عَلَيْهِمْ سَبْعَ لَيَالٍ وَثَمَانِيَةَ أَيَّامٍ حُسُومًا فَتَرَى الْقَوْمَ فِيهَا صَرْعَىٰ كَأَنَّهُمْ أَعْجَازُ نَخْلٍ خَاوِيَةٍ",
            "bnText": "যা তিনি প্রবাহিত করেছিলেন তাদের উপর সাত রাত্রি ও আট দিবস পর্যন্ত অবিরাম। আপনি তাদেরকে দেখতেন যে, তারা অসার খর্জুর কান্ডের ন্যায় ভূপাতিত হয়ে রয়েছে।",
            "enText": "Which Allah imposed upon them for seven nights and eight days in succession, so you would see the people therein fallen as if they were hollow trunks of palm trees.",
            "enTextTransliteration": "Sakhkharahaa 'alaihim sab'a la yaalinw wa samaaniyata ayyaamin husooman fataral qawma feehaa sar'aa ka annahum a'jaazu nakhlin khaawiyah",
            "audioPrimary": "https://cdn.alquran.cloud/media/audio/ayah/ar.alafasy/5330",
            "numberInSurah": 7
        },
        {
            "text": "فَهَلْ تَرَىٰ لَهُم مِّن بَاقِيَةٍ",
            "bnText": "আপনি তাদের কোন অস্তিত্ব দেখতে পান কি",
            "enText": "Then do you see of them any remains?",
            "enTextTransliteration": "Fahal taraa lahum mim baaqiyah",
            "audioPrimary": "https://cdn.alquran.cloud/media/audio/ayah/ar.alafasy/5331",
            "numberInSurah": 8
        },
        {
            "text": "وَجَاءَ فِرْعَوْنُ وَمَن قَبْلَهُ وَالْمُؤْتَفِكَاتُ بِالْخَاطِئَةِ",
            "bnText": "ফেরাউন, তাঁর পূর্ববর্তীরা এবং উল্টে যাওয়া বস্তিবাসীরা গুরুতর পাপ করেছিল।",
            "enText": "And there came Pharaoh and those before him and the overturned cities with sin.",
            "enTextTransliteration": "Wa jaaa'a Firawnu wa man qablahoo wal mu'tafikaatu bilhaati'ah",
            "audioPrimary": "https://cdn.alquran.cloud/media/audio/ayah/ar.alafasy/5332",
            "numberInSurah": 9
        },
        {
            "text": "فَعَصَوْا رَسُولَ رَبِّهِمْ فَأَخَذَهُمْ أَخْذَةً رَّابِيَةً",
            "bnText": "তারা তাদের পালনকর্তার রসূলকে অমান্য করেছিল। ফলে তিনি তাদেরকে কঠোরহস্তে পাকড়াও করলেন।",
            "enText": "And they disobeyed the messenger of their Lord, so He seized them with a seizure exceeding [in severity].",
            "enTextTransliteration": "Fa'ansaw Rasoola Rabbihim fa akhazahum akhzatar raabiyah",
            "audioPrimary": "https://cdn.alquran.cloud/media/audio/ayah/ar.alafasy/5333",
            "numberInSurah": 10
        },
        {
            "text": "إِنَّا لَمَّا طَغَى الْمَاءُ حَمَلْنَاكُمْ فِي الْجَارِيَةِ",
            "bnText": "যখন জলোচ্ছ্বাস হয়েছিল, তখন আমি তোমাদেরকে চলন্ত নৌযানে আরোহণ করিয়েছিলাম।",
            "enText": "Indeed, when the water overflowed, We carried your ancestors in the sailing ship",
            "enTextTransliteration": "Innaa lammaa taghal maaa'u hamalnaakum fil jaariyah",
            "audioPrimary": "https://cdn.alquran.cloud/media/audio/ayah/ar.alafasy/5334",
            "numberInSurah": 11
        },
        {
            "text": "لِنَجْعَلَهَا لَكُمْ تَذْكِرَةً وَتَعِيَهَا أُذُنٌ وَاعِيَةٌ",
            "bnText": "যাতে এ ঘটনা তোমাদের জন্যে স্মৃতির বিষয় এবং কান এটাকে উপদেশ গ্রহণের উপযোগী রূপে গ্রহণ করে।",
            "enText": "That We might make it for you a reminder and [that] a conscious ear would be conscious of it.",
            "enTextTransliteration": "Linaj'alahaa lakum tazki ratanw-wa ta'iyahaa unzununw waa'iyah",
            "audioPrimary": "https://cdn.alquran.cloud/media/audio/ayah/ar.alafasy/5335",
            "numberInSurah": 12
        },
        {
            "text": "فَإِذَا نُفِخَ فِي الصُّورِ نَفْخَةٌ وَاحِدَةٌ",
            "bnText": "যখন শিংগায় ফুৎকার দেয়া হবে-একটি মাত্র ফুৎকার",
            "enText": "Then when the Horn is blown with one blast",
            "enTextTransliteration": "Fa izaa nufikha fis soori nafkhatunw waahidah",
            "audioPrimary": "https://cdn.alquran.cloud/media/audio/ayah/ar.alafasy/5336",
            "numberInSurah": 13
        },
        {
            "text": "وَحُمِلَتِ الْأَرْضُ وَالْجِبَالُ فَدُكَّتَا دَكَّةً وَاحِدَةً",
            "bnText": "এবং পৃথিবী ও পর্বতমালা উত্তোলিত হবে ও চুর্ণ-বিচুর্ণ করে দেয়া হবে",
            "enText": "And the earth and the mountains are lifted and leveled with one blow -",
            "enTextTransliteration": "Wa humilatil ardu wal jibaalu fadukkataa dakkatanw waahidah",
            "audioPrimary": "https://cdn.alquran.cloud/media/audio/ayah/ar.alafasy/5337",
            "numberInSurah": 14
        },
        {
            "text": "فَيَوْمَئِذٍ وَقَعَتِ الْوَاقِعَةُ",
            "bnText": "সেদিন কেয়ামত সংঘটিত হবে।",
            "enText": "Then on that Day, the Resurrection will occur,",
            "enTextTransliteration": "Fa yawma'izinw waqa'atil waaqi'ah",
            "audioPrimary": "https://cdn.alquran.cloud/media/audio/ayah/ar.alafasy/5338",
            "numberInSurah": 15
        },
        {
            "text": "وَانشَقَّتِ السَّمَاءُ فَهِيَ يَوْمَئِذٍ وَاهِيَةٌ",
            "bnText": "সেদিন আকাশ বিদীর্ণ হবে ও বিক্ষিপ্ত হবে।",
            "enText": "And the heaven will split [open], for that Day it is infirm.",
            "enTextTransliteration": "Wanshaqqatis samaaa'u fahiya yawma 'izinw-waahiyah",
            "audioPrimary": "https://cdn.alquran.cloud/media/audio/ayah/ar.alafasy/5339",
            "numberInSurah": 16
        },
        {
            "text": "وَالْمَلَكُ عَلَىٰ أَرْجَائِهَا ۚ وَيَحْمِلُ عَرْشَ رَبِّكَ فَوْقَهُمْ يَوْمَئِذٍ ثَمَانِيَةٌ",
            "bnText": "এবং ফেরেশতাগণ আকাশের প্রান্তদেশে থাকবে ও আট জন ফেরেশতা আপনার পালনকর্তার আরশকে তাদের উর্ধ্বে বহন করবে।",
            "enText": "And the angels are at its edges. And there will bear the Throne of your Lord above them, that Day, eight [of them].",
            "enTextTransliteration": "Wal malaku 'alaaa arjaaa'ihaa; wa yahmilu 'Arsha Rabbika fawqahum yawma'izin samaaniyah",
            "audioPrimary": "https://cdn.alquran.cloud/media/audio/ayah/ar.alafasy/5340",
            "numberInSurah": 17
        },
        {
            "text": "يَوْمَئِذٍ تُعْرَضُونَ لَا تَخْفَىٰ مِنكُمْ خَافِيَةٌ",
            "bnText": "সেদিন তোমাদেরকে উপস্থিত করা হবে। তোমাদের কোন কিছু গোপন থাকবে না।",
            "enText": "That Day, you will be exhibited [for judgement]; not hidden among you is anything concealed.",
            "enTextTransliteration": "Yawma'izin tu'radoona laa takhfaa min kum khaafiyah",
            "audioPrimary": "https://cdn.alquran.cloud/media/audio/ayah/ar.alafasy/5341",
            "numberInSurah": 18
        },
        {
            "text": "فَأَمَّا مَنْ أُوتِيَ كِتَابَهُ بِيَمِينِهِ فَيَقُولُ هَاؤُمُ اقْرَءُوا كِتَابِيَهْ",
            "bnText": "অতঃপর যার আমলনামা ডান হাতে দেয়া হবে, সে বলবেঃ নাও, তোমরাও আমলনামা পড়ে দেখ।",
            "enText": "So as for he who is given his record in his right hand, he will say, \"Here, read my record!",
            "enTextTransliteration": "Fa ammaa man ootiya kitaabahoo biyameenihee fa yaqoolu haaa'umuq ra'oo kitaabiyah",
            "audioPrimary": "https://cdn.alquran.cloud/media/audio/ayah/ar.alafasy/5342",
            "numberInSurah": 19
        },
        {
            "text": "إِنِّي ظَنَنتُ أَنِّي مُلَاقٍ حِسَابِيَهْ",
            "bnText": "আমি জানতাম যে, আমাকে হিসাবের সম্মুখীন হতে হবে।",
            "enText": "Indeed, I was certain that I would be meeting my account.\"",
            "enTextTransliteration": "Innee zannantu annee mulaaqin hisaabiyah",
            "audioPrimary": "https://cdn.alquran.cloud/media/audio/ayah/ar.alafasy/5343",
            "numberInSurah": 20
        },
        {
            "text": "فَهُوَ فِي عِيشَةٍ رَّاضِيَةٍ",
            "bnText": "অতঃপর সে সুখী জীবন-যাপন করবে",
            "enText": "So he will be in a pleasant life -",
            "enTextTransliteration": "Fahuwa fee 'eeshatir raadiyah",
            "audioPrimary": "https://cdn.alquran.cloud/media/audio/ayah/ar.alafasy/5344",
            "numberInSurah": 21
        },
        {
            "text": "فِي جَنَّةٍ عَالِيَةٍ",
            "bnText": "সুউচ্চ জান্নাতে।",
            "enText": "In an elevated garden,",
            "enTextTransliteration": "Fee jannnatin 'aaliyah",
            "audioPrimary": "https://cdn.alquran.cloud/media/audio/ayah/ar.alafasy/5345",
            "numberInSurah": 22
        },
        {
            "text": "قُطُوفُهَا دَانِيَةٌ",
            "bnText": "তার ফলসমূহ অবনমিত থাকবে।",
            "enText": "Its [fruit] to be picked hanging near.",
            "enTextTransliteration": "Qutoofuhaa daaniyah",
            "audioPrimary": "https://cdn.alquran.cloud/media/audio/ayah/ar.alafasy/5346",
            "numberInSurah": 23
        },
        {
            "text": "كُلُوا وَاشْرَبُوا هَنِيئًا بِمَا أَسْلَفْتُمْ فِي الْأَيَّامِ الْخَالِيَةِ",
            "bnText": "বিগত দিনে তোমরা যা প্রেরণ করেছিলে, তার প্রতিদানে তোমরা খাও এবং পান কর তৃপ্তি সহকারে।",
            "enText": "[They will be told], \"Eat and drink in satisfaction for what you put forth in the days past.\"",
            "enTextTransliteration": "Kuloo washraboo haneee'am bimaaa aslaftum fil ayyaamil khaliyah",
            "audioPrimary": "https://cdn.alquran.cloud/media/audio/ayah/ar.alafasy/5347",
            "numberInSurah": 24
        },
        {
            "text": "وَأَمَّا مَنْ أُوتِيَ كِتَابَهُ بِشِمَالِهِ فَيَقُولُ يَا لَيْتَنِي لَمْ أُوتَ كِتَابِيَهْ",
            "bnText": "যার আমলনামা তার বাম হাতে দেয়া হবে, সে বলবেঃ হায় আমায় যদি আমার আমল নামা না দেয়া হতো।",
            "enText": "But as for he who is given his record in his left hand, he will say, \"Oh, I wish I had not been given my record",
            "enTextTransliteration": "Wa ammaa man ootiya kitaabahoo bishimaalihee fa yaqoolu yaalaitanee lam oota kitaaabiyah",
            "audioPrimary": "https://cdn.alquran.cloud/media/audio/ayah/ar.alafasy/5348",
            "numberInSurah": 25
        },
        {
            "text": "وَلَمْ أَدْرِ مَا حِسَابِيَهْ",
            "bnText": "আমি যদি না জানতাম আমার হিসাব",
            "enText": "And had not known what is my account.",
            "enTextTransliteration": "Wa lam adri maa hisaabiyah",
            "audioPrimary": "https://cdn.alquran.cloud/media/audio/ayah/ar.alafasy/5349",
            "numberInSurah": 26
        },
        {
            "text": "يَا لَيْتَهَا كَانَتِ الْقَاضِيَةَ",
            "bnText": "হায়, আমার মৃত্যুই যদি শেষ হত।",
            "enText": "I wish my death had been the decisive one.",
            "enTextTransliteration": "Yaa laitahaa kaanatil qaadiyah",
            "audioPrimary": "https://cdn.alquran.cloud/media/audio/ayah/ar.alafasy/5350",
            "numberInSurah": 27
        },
        {
            "text": "مَا أَغْنَىٰ عَنِّي مَالِيَهْ ۜ",
            "bnText": "আমার ধন-সম্পদ আমার কোন উপকারে আসল না।",
            "enText": "My wealth has not availed me.",
            "enTextTransliteration": "Maaa aghnaa 'annee maaliyah",
            "audioPrimary": "https://cdn.alquran.cloud/media/audio/ayah/ar.alafasy/5351",
            "numberInSurah": 28
        },
        {
            "text": "هَلَكَ عَنِّي سُلْطَانِيَهْ",
            "bnText": "আমার ক্ষমতাও বরবাদ হয়ে গেল।",
            "enText": "Gone from me is my authority.\"",
            "enTextTransliteration": "Halaka 'annee sultaaniyah",
            "audioPrimary": "https://cdn.alquran.cloud/media/audio/ayah/ar.alafasy/5352",
            "numberInSurah": 29
        },
        {
            "text": "خُذُوهُ فَغُلُّوهُ",
            "bnText": "ফেরেশতাদেরকে বলা হবেঃ ধর একে গলায় বেড়ি পড়িয়ে দাও",
            "enText": "[Allah will say], \"Seize him and shackle him.",
            "enTextTransliteration": "Khuzoohu faghullooh",
            "audioPrimary": "https://cdn.alquran.cloud/media/audio/ayah/ar.alafasy/5353",
            "numberInSurah": 30
        },
        {
            "text": "ثُمَّ الْجَحِيمَ صَلُّوهُ",
            "bnText": "অতঃপর নিক্ষেপ কর জাহান্নামে।",
            "enText": "Then into Hellfire drive him.",
            "enTextTransliteration": "Summal Jaheema sallooh",
            "audioPrimary": "https://cdn.alquran.cloud/media/audio/ayah/ar.alafasy/5354",
            "numberInSurah": 31
        },
        {
            "text": "ثُمَّ فِي سِلْسِلَةٍ ذَرْعُهَا سَبْعُونَ ذِرَاعًا فَاسْلُكُوهُ",
            "bnText": "অতঃপর তাকে শৃঙ্খলিত কর সত্তর গজ দীর্ঘ এক শিকলে।",
            "enText": "Then into a chain whose length is seventy cubits insert him.\"",
            "enTextTransliteration": "Summa fee silsilatin zar'uhaa sab'oona ziraa'an faslukooh",
            "audioPrimary": "https://cdn.alquran.cloud/media/audio/ayah/ar.alafasy/5355",
            "numberInSurah": 32
        },
        {
            "text": "إِنَّهُ كَانَ لَا يُؤْمِنُ بِاللَّهِ الْعَظِيمِ",
            "bnText": "নিশ্চয় সে মহান আল্লাহতে বিশ্বাসী ছিল না।",
            "enText": "Indeed, he did not used to believe in Allah, the Most Great,",
            "enTextTransliteration": "Innahoo kaana laa yu'minubillaahil 'Azeem",
            "audioPrimary": "https://cdn.alquran.cloud/media/audio/ayah/ar.alafasy/5356",
            "numberInSurah": 33
        },
        {
            "text": "وَلَا يَحُضُّ عَلَىٰ طَعَامِ الْمِسْكِينِ",
            "bnText": "এবং মিসকীনকে আহার্য দিতে উৎসাহিত করত না।",
            "enText": "Nor did he encourage the feeding of the poor.",
            "enTextTransliteration": "wa laa yahuddu 'alaa ta'aamil miskeen",
            "audioPrimary": "https://cdn.alquran.cloud/media/audio/ayah/ar.alafasy/5357",
            "numberInSurah": 34
        },
        {
            "text": "فَلَيْسَ لَهُ الْيَوْمَ هَاهُنَا حَمِيمٌ",
            "bnText": "অতএব, আজকের দিন এখানে তার কোন সুহূদ নাই।",
            "enText": "So there is not for him here this Day any devoted friend",
            "enTextTransliteration": "Falaysa lahul yawma haahunaa hameem",
            "audioPrimary": "https://cdn.alquran.cloud/media/audio/ayah/ar.alafasy/5358",
            "numberInSurah": 35
        },
        {
            "text": "وَلَا طَعَامٌ إِلَّا مِنْ غِسْلِينٍ",
            "bnText": "এবং কোন খাদ্য নাই, ক্ষত-নিঃসৃত পুঁজ ব্যতীত।",
            "enText": "Nor any food except from the discharge of wounds;",
            "enTextTransliteration": "Wa laa ta'aamun illaa min ghisleen",
            "audioPrimary": "https://cdn.alquran.cloud/media/audio/ayah/ar.alafasy/5359",
            "numberInSurah": 36
        },
        {
            "text": "لَّا يَأْكُلُهُ إِلَّا الْخَاطِئُونَ",
            "bnText": "গোনাহগার ব্যতীত কেউ এটা খাবে না।",
            "enText": "None will eat it except the sinners.",
            "enTextTransliteration": "Laa yaakuluhooo illal khati'oon",
            "audioPrimary": "https://cdn.alquran.cloud/media/audio/ayah/ar.alafasy/5360",
            "numberInSurah": 37
        },
        {
            "text": "فَلَا أُقْسِمُ بِمَا تُبْصِرُونَ",
            "bnText": "তোমরা যা দেখ, আমি তার শপথ করছি।",
            "enText": "So I swear by what you see",
            "enTextTransliteration": "Falaaa uqsimu bimaa tubsiroon",
            "audioPrimary": "https://cdn.alquran.cloud/media/audio/ayah/ar.alafasy/5361",
            "numberInSurah": 38
        },
        {
            "text": "وَمَا لَا تُبْصِرُونَ",
            "bnText": "এবং যা তোমরা দেখ না, তার",
            "enText": "And what you do not see",
            "enTextTransliteration": "Wa maa laa tubsiroon",
            "audioPrimary": "https://cdn.alquran.cloud/media/audio/ayah/ar.alafasy/5362",
            "numberInSurah": 39
        },
        {
            "text": "إِنَّهُ لَقَوْلُ رَسُولٍ كَرِيمٍ",
            "bnText": "নিশ্চয়ই এই কোরআন একজন সম্মানিত রসূলের আনীত।",
            "enText": "[That] indeed, the Qur'an is the word of a noble Messenger.",
            "enTextTransliteration": "Innahoo laqawlu Rasoolin kareem",
            "audioPrimary": "https://cdn.alquran.cloud/media/audio/ayah/ar.alafasy/5363",
            "numberInSurah": 40
        },
        {
            "text": "وَمَا هُوَ بِقَوْلِ شَاعِرٍ ۚ قَلِيلًا مَّا تُؤْمِنُونَ",
            "bnText": "এবং এটা কোন কবির কালাম নয়; তোমরা কমই বিশ্বাস কর।",
            "enText": "And it is not the word of a poet; little do you believe.",
            "enTextTransliteration": "Wa ma huwa biqawli shaa'ir; qaleelam maa tu'minoon",
            "audioPrimary": "https://cdn.alquran.cloud/media/audio/ayah/ar.alafasy/5364",
            "numberInSurah": 41
        },
        {
            "text": "وَلَا بِقَوْلِ كَاهِنٍ ۚ قَلِيلًا مَّا تَذَكَّرُونَ",
            "bnText": "এবং এটা কোন অতীন্দ্রিয়বাদীর কথা নয়; তোমরা কমই অনুধাবন কর।",
            "enText": "Nor the word of a soothsayer; little do you remember.",
            "enTextTransliteration": "Wa laa biqawli kaahin; qaleelam maa tazakkaroon",
            "audioPrimary": "https://cdn.alquran.cloud/media/audio/ayah/ar.alafasy/5365",
            "numberInSurah": 42
        },
        {
            "text": "تَنزِيلٌ مِّن رَّبِّ الْعَالَمِينَ",
            "bnText": "এটা বিশ্বপালনকর্তার কাছ থেকে অবতীর্ণ।",
            "enText": "[It is] a revelation from the Lord of the worlds.",
            "enTextTransliteration": "Tanzeelum mir rabbil 'aalameen",
            "audioPrimary": "https://cdn.alquran.cloud/media/audio/ayah/ar.alafasy/5366",
            "numberInSurah": 43
        },
        {
            "text": "وَلَوْ تَقَوَّلَ عَلَيْنَا بَعْضَ الْأَقَاوِيلِ",
            "bnText": "সে যদি আমার নামে কোন কথা রচনা করত",
            "enText": "And if Muhammad had made up about Us some [false] sayings,",
            "enTextTransliteration": "Wa law taqawwala 'alainaa ba'dal aqaaweel",
            "audioPrimary": "https://cdn.alquran.cloud/media/audio/ayah/ar.alafasy/5367",
            "numberInSurah": 44
        },
        {
            "text": "لَأَخَذْنَا مِنْهُ بِالْيَمِينِ",
            "bnText": "তবে আমি তার দক্ষিণ হস্ত ধরে ফেলতাম",
            "enText": "We would have seized him by the right hand;",
            "enTextTransliteration": "La-akhaznaa minhu bilyameen",
            "audioPrimary": "https://cdn.alquran.cloud/media/audio/ayah/ar.alafasy/5368",
            "numberInSurah": 45
        },
        {
            "text": "ثُمَّ لَقَطَعْنَا مِنْهُ الْوَتِينَ",
            "bnText": "অতঃপর কেটে দিতাম তার গ্রীবা।",
            "enText": "Then We would have cut from him the aorta.",
            "enTextTransliteration": "Summa laqata'naa minhul wateen",
            "audioPrimary": "https://cdn.alquran.cloud/media/audio/ayah/ar.alafasy/5369",
            "numberInSurah": 46
        },
        {
            "text": "فَمَا مِنكُم مِّنْ أَحَدٍ عَنْهُ حَاجِزِينَ",
            "bnText": "তোমাদের কেউ তাকে রক্ষা করতে পারতে না।",
            "enText": "And there is no one of you who could prevent [Us] from him.",
            "enTextTransliteration": "Famaa minkum min ahadin'anhu haajizeen",
            "audioPrimary": "https://cdn.alquran.cloud/media/audio/ayah/ar.alafasy/5370",
            "numberInSurah": 47
        },
        {
            "text": "وَإِنَّهُ لَتَذْكِرَةٌ لِّلْمُتَّقِينَ",
            "bnText": "এটা খোদাভীরুদের জন্যে অবশ্যই একটি উপদেশ।",
            "enText": "And indeed, the Qur'an is a reminder for the righteous.",
            "enTextTransliteration": "Wa innahoo latazkiratul lilmuttaqeen",
            "audioPrimary": "https://cdn.alquran.cloud/media/audio/ayah/ar.alafasy/5371",
            "numberInSurah": 48
        },
        {
            "text": "وَإِنَّا لَنَعْلَمُ أَنَّ مِنكُم مُّكَذِّبِينَ",
            "bnText": "আমি জানি যে, তোমাদের মধ্যে কেউ কেউ মিথ্যারোপ করবে।",
            "enText": "And indeed, We know that among you are deniers.",
            "enTextTransliteration": "Wa inna lana'lamu anna minkum mukazzibeen",
            "audioPrimary": "https://cdn.alquran.cloud/media/audio/ayah/ar.alafasy/5372",
            "numberInSurah": 49
        },
        {
            "text": "وَإِنَّهُ لَحَسْرَةٌ عَلَى الْكَافِرِينَ",
            "bnText": "নিশ্চয় এটা কাফেরদের জন্যে অনুতাপের কারণ।",
            "enText": "And indeed, it will be [a cause of] regret upon the disbelievers.",
            "enTextTransliteration": "Wa innahu lahasratun 'alal kaafireen",
            "audioPrimary": "https://cdn.alquran.cloud/media/audio/ayah/ar.alafasy/5373",
            "numberInSurah": 50
        },
        {
            "text": "وَإِنَّهُ لَحَقُّ الْيَقِينِ",
            "bnText": "নিশ্চয় এটা নিশ্চিত সত্য।",
            "enText": "And indeed, it is the truth of certainty.",
            "enTextTransliteration": "Wa innahoo lahaqqul yaqeen",
            "audioPrimary": "https://cdn.alquran.cloud/media/audio/ayah/ar.alafasy/5374",
            "numberInSurah": 51
        },
        {
            "text": "فَسَبِّحْ بِاسْمِ رَبِّكَ الْعَظِيمِ",
            "bnText": "অতএব, আপনি আপনার মহান পালনকর্তার নামের পবিত্রতা বর্ননা করুন।",
            "enText": "So exalt the name of your Lord, the Most Great.",
            "enTextTransliteration": "Fasbbih bismi Rabbikal 'Azeem",
            "audioPrimary": "https://cdn.alquran.cloud/media/audio/ayah/ar.alafasy/5375",
            "numberInSurah": 52
        }
    ]
}